[
  {
    "id": "barrier1",
    "template": "barrier_wood_top_left.json",
    "properties": {
    },
    "eventsAction": [
      {
        "action": {
          "type": "SET_STATE",
          "value": "OPEN"
        },
        "inputEvents": [
          {
            "sourceId": "activator1",
            "type": "STATE",
            "value": "ACTIVATED"
          }
        ]
      },
      {
        "action": {
          "type": "OPEN",
          "value": ""
        },
        "inputEvents": [
          {
            "sourceId": "barrier1",
            "type": "STATE",
            "value": "OPEN"
          }
        ]
      },
      {
        "action": {
        "type": "SET_STATE",
        "value": "CLOSED"
      },
        "inputEvents": [
          {
            "sourceId": "activator1",
            "type": "STATE",
            "value": "IDLE"
          }
        ]
      },
      {
        "action": {
          "type": "CLOSE",
          "value": ""
        },
        "inputEvents": [
          {
            "sourceId": "barrier1",
            "type": "STATE",
            "value": "CLOSED"
          }
        ]
      }
    ],
    "outputEvents": [
      {
        "type": "STATE",
        "value": "CLOSED"
      },
      {
        "type": "STATE",
        "value": "OPEN"
      }
    ]
  },
  {
    "id": "activator1",
    "template": "activator_type1.json"
  },
  {
    "id": "barrier2",
    "template": "barrier_wood_bottom_left.json",
    "properties": {
    },
    "eventsAction": [
      {
        "action": {
          "type": "SET_STATE",
          "value": "OPEN"
        },
        "inputEvents": [
          {
            "sourceId": "activator2",
            "type": "STATE",
            "value": "ACTIVATED"
          }
        ]
      },
      {
        "action": {
          "type": "OPEN",
          "value": ""
        },
        "inputEvents": [
          {
            "sourceId": "barrier2",
            "type": "STATE",
            "value": "OPEN"
          }
        ]
      },
      {
        "action": {
          "type": "SET_STATE",
          "value": "CLOSED"
        },
        "inputEvents": [
          {
            "sourceId": "activator2",
            "type": "STATE",
            "value": "IDLE"
          }
        ]
      },
      {
        "action": {
          "type": "CLOSE",
          "value": ""
        },
        "inputEvents": [
          {
            "sourceId": "barrier2",
            "type": "STATE",
            "value": "CLOSED"
          }
        ]
      }
    ],
    "outputEvents": [
      {
        "type": "STATE",
        "value": "CLOSED"
      },
      {
        "type": "STATE",
        "value": "OPEN"
      }
    ]
  },
  {
    "id": "activator2",
    "template": "activator_type1.json"
  },
  {
    "id": "barrier3",
    "template": "barrier_wood_right_top.json",
    "properties": {
    },
    "eventsAction": [
      {
        "action": {
          "type": "SET_STATE",
          "value": "OPEN"
        },
        "inputEvents": [
          {
            "sourceId": "activator3",
            "type": "STATE",
            "value": "ACTIVATED"
          }
        ]
      },
      {
        "action": {
          "type": "OPEN",
          "value": ""
        },
        "inputEvents": [
          {
            "sourceId": "barrier3",
            "type": "STATE",
            "value": "OPEN"
          }
        ]
      },
      {

        "action": {
          "type": "SET_STATE",
          "value": "CLOSED"
        },
        "inputEvents": [
          {
            "sourceId": "activator3",
            "type": "STATE",
            "value": "IDLE"
          }
        ]
      },
      {
        "action": {
          "type": "CLOSE",
          "value": ""
        },
        "inputEvents": [
          {
            "sourceId": "barrier3",
            "type": "STATE",
            "value": "CLOSED"
          }
        ]
      }
    ],
    "outputEvents": [
      {
        "type": "STATE",
        "value": "CLOSED"
      },
      {
        "type": "STATE",
        "value": "OPEN"
      }
    ]
  },
  {
    "id": "activator3",
    "template": "activator_type1.json"
  },
  {
    "id": "barrier4",
    "template": "barrier_wood_left_bottom.json",
    "properties": {
    },
    "eventsAction": [
      {
        "action": {
          "type": "SET_STATE",
          "value": "OPEN"
        },
        "inputEvents": [
          {
            "sourceId": "activator4",
            "type": "STATE",
            "value": "ACTIVATED"
          }
        ]
      },
      {
        "action": {
          "type": "SET_STATE",
          "value": "OPEN"
        },
        "inputEvents": [
          {
            "sourceId": "activator5",
            "type": "STATE",
            "value": "ACTIVATED"
          }
        ]
      },
      {
        "action": {
          "type": "OPEN",
          "value": ""
        },
        "inputEvents": [
          {
            "sourceId": "barrier4",
            "type": "STATE",
            "value": "OPEN"
          }
        ]
      },
      {
        "action": {
          "type": "SET_STATE",
          "value": "CLOSED"
        },
        "inputEvents": [
          {
            "sourceId": "activator4",
            "type": "STATE",
            "value": "IDLE"
          }
        ]
      },
      {
        "action": {
          "type": "SET_STATE",
          "value": "CLOSED"
        },
        "inputEvents": [
          {
            "sourceId": "activator5",
            "type": "STATE",
            "value": "IDLE"
          }
        ]
      },
      {
        "action": {
          "type": "CLOSE",
          "value": ""
        },
        "inputEvents": [
          {
            "sourceId": "barrier4",
            "type": "STATE",
            "value": "CLOSED"
          }
        ]
      }
    ],
    "outputEvents": [
      {
        "type": "STATE",
        "value": "CLOSED"
      },
      {
        "type": "STATE",
        "value": "OPEN"
      }
    ]
  },
  {
    "id": "activator4",
    "template": "activator_type1.json"
  },
  {
    "id": "activator5",
    "template": "activator_type1.json"
  },
  {
    "id": "portal1",
    "template": "portal.json",
    "properties": {
      "targetMapId": "village",
      "isDefaultStart": "true"
    },
    "eventsAction": [],
    "outputEvents": []
  },
  {
    "id": "portal2",
    "template": "portal.json",
    "properties": {
      "targetMapId": "east_land2"
    },
    "eventsAction": [],
    "outputEvents": []
  }
]